brain_modules/__init__.py
brain_modules/utils.py
brain_modules/utils_plot.py
brain_modules-0.0.6.dist-info/METADATA
brain_modules-0.0.6.dist-info/WHEEL
brain_modules-0.0.6.dist-info/top_level.txt
brain_modules-0.0.6.dist-info/RECORD
