Metadata-Version: 2.4
Name: brain-modules
Version: 0.0.6
Summary: Replicate brain modules' computations with Artificial Neural Networks
Home-page: https://github.com/NeuroAI-Research/brain-modules
Author: Ricky Ding
Author-email: e0134117@u.nus.edu
License: MIT
Keywords: neuroscience,neuroAI,artificial-intelligence,neural-networks,cognitive-modeling,brain-modules
Classifier: Programming Language :: Python :: 3
Classifier: License :: OSI Approved :: MIT License
Classifier: Operating System :: OS Independent
Classifier: Topic :: Scientific/Engineering :: Artificial Intelligence
Requires-Python: >=3.8
Requires-Dist: gymnasium
Requires-Dist: torch
Requires-Dist: matplotlib
Dynamic: author
Dynamic: author-email
Dynamic: classifier
Dynamic: description
Dynamic: description-content-type
Dynamic: home-page
Dynamic: keywords
Dynamic: license
Dynamic: requires-dist
Dynamic: requires-python
Dynamic: summary
